[
  {
    "TRANSFORM": {
      "position": {
        "x": 2.009999990463257,
        "y": 9.255000114440918,
        "z": -5.11899995803833
      },
      "scale": {
        "x": 5.0,
        "y": 5.0,
        "z": 5.0
      },
      "rotation": {
        "x": 0.0,
        "y": 0.0,
        "z": 7.549785152605182e-08,
        "w": 1.0
      }
    },
    "LIGHT": {
      "Color": {
        "x": 1.0,
        "y": 0.6000000238418579,
        "z": 0.6000000238418579
      },
      "Intensity": {
        "x": 3.0,
        "y": 3.0,
        "z": 3.0
      },
      "LightType": 0,
      "Target": {
        "x": 0.0,
        "y": -1.0,
        "z": 0.0
      }
    },
    "TAG": {
      "uniqueName": "",
      "category": ""
    }
  },
  {
    "MODEL": {
      "path": "../Platformer/Assets/Models/placeholder_platforms.obj"
    },
    "TRANSFORM": {
      "position": {
        "x": 0.0,
        "y": 6.199999809265137,
        "z": 0.0
      },
      "scale": {
        "x": 50.0,
        "y": 3.0199999809265137,
        "z": 7.0
      },
      "rotation": {
        "x": 0.0,
        "y": 0.0,
        "z": 0.0,
        "w": 1.0
      }
    },
    "MATERIAL": {
      "AlbedoPath": "../Platformer/Assets/Textures/PlatformBaseColor.png",
      "MetallicPath": "../Platformer/Assets/Textures/metal_Tex/metallic.png",
      "Alpha": 1.0,
      "wireMode": false
    },
    "COLLIDER": {
      "Shape": 1,
      "Normal": {
        "x": 0.0,
        "y": 1.0,
        "z": 0.0
      },
      "Magnitude": 6.199999809265137
    },
    "STILL_BODY": {
      "Shape": 0,
      "Radius": 1.0
    },
    "TAG": {
      "uniqueName": "BasePlayerPlatform",
      "category": "Slope"
    }
  },
  {
    "MODEL": {
      "path": "../Platformer/Assets/Models/plane.obj"
    },
    "TRANSFORM": {
      "position": {
        "x": 1.559999942779541,
        "y": 50.18000030517578,
        "z": 39.2599983215332
      },
      "scale": {
        "x": 50.37900161743164,
        "y": 1.2330000400543213,
        "z": 50.24700164794922
      },
      "rotation": {
        "x": -0.5000001192092896,
        "y": -0.49999991059303284,
        "z": 0.49999991059303284,
        "w": 0.5000001192092896
      }
    },
    "MATERIAL": {
      "AlbedoPath": "../Platformer/Assets/Textures/Gradient Background.png",
      "MetallicPath": "../Platformer/Assets/Textures/wall/metallic.png",
      "Alpha": 1.0,
      "wireMode": false
    },
    "TAG": {
      "uniqueName": "wall plane",
      "category": ""
    }
  },
  {
    "MODEL": {
      "path": "../Platformer/Assets/Models/Goal.obj"
    },
    "TRANSFORM": {
      "position": {
        "x": 24.790000915527344,
        "y": 2.0,
        "z": 33.66999816894531
      },
      "scale": {
        "x": 2.0,
        "y": 1.0,
        "z": 2.0
      },
      "rotation": {
        "x": 0.0,
        "y": 0.7069846987724304,
        "z": 0.0,
        "w": 0.7072288393974304
      }
    },
    "MATERIAL": {
      "AlbedoPath": "Assets/Textures/Goal Base Color.png",
      "MetallicPath": "Assets/Textures/Goal Specular.png",
      "Alpha": 1.0,
      "wireMode": false
    },
    "COLLIDER": {
      "Shape": 2,
      "MinPoint": {
        "x": -2.0,
        "y": -1.0,
        "z": -3.0
      },
      "MaxPoint": {
        "x": 2.0,
        "y": 1.0,
        "z": 3.0
      }
    },
    "STILL_BODY": {
      "Shape": 0,
      "Radius": 1.0
    },
    "GAME_LOGIC": [
      "MOVING_PLATFORM"
    ],
    "TAG": {
      "uniqueName": "Goal",
      "category": "Goal"
    }
  },
  {
    "TAG": {
      "uniqueName": "",
      "category": ""
    }
  },
  {
    "TAG": {
      "uniqueName": "",
      "category": ""
    }
  },
  {
    "TAG": {
      "uniqueName": "",
      "category": ""
    }
  },
  {
    "TAG": {
      "uniqueName": "",
      "category": ""
    }
  },
  {
    "MODEL": {
      "path": "../Platformer/Assets/Models/Ball.obj"
    },
    "TRANSFORM": {
      "position": {
        "x": 39.377357482910156,
        "y": 9.133200645446777,
        "z": 1.0
      },
      "scale": {
        "x": 3.0,
        "y": 3.0,
        "z": 3.0
      },
      "rotation": {
        "x": 0.0,
        "y": 0.0,
        "z": 0.8181515336036682,
        "w": 0.5750026702880859
      }
    },
    "MATERIAL": {
      "AlbedoPath": "../Platformer/Assets/Textures/Hero Base Color.png",
      "MetallicPath": "../Platformer/Assets/Textures/Ball Specular.png",
      "Alpha": 1.0,
      "wireMode": false
    },
    "COLLIDER": {
      "Shape": 0,
      "Radius": 2.930000066757202
    },
    "MOVING_BODY": {
      "Elasticity": 0.3499999940395355,
      "Friction": 0.0,
      "Gravity": true,
      "Mass": 5.0,
      "Velocity": {
        "x": 0.0,
        "y": -0.5740704536437988,
        "z": 0.0
      },
      "Accelereation": {
        "x": 0.0,
        "y": 0.0,
        "z": 0.0
      },
      "CollisionType": 0,
      "Shape": 0,
      "Radius": 1.0
    },
    "GAME_LOGIC": [
      "PLAYER"
    ],
    "TAG": {
      "uniqueName": "Player",
      "category": "Player"
    }
  },
  {
    "MODEL": {
      "path": "../Platformer/Assets/Models/Ball.obj"
    },
    "TRANSFORM": {
      "position": {
        "x": 24.215999603271484,
        "y": -2004.6300048828125,
        "z": 35.0
      },
      "scale": {
        "x": 3.0,
        "y": 3.0,
        "z": 3.0
      },
      "rotation": {
        "x": 0.0,
        "y": 0.0,
        "z": 0.0,
        "w": 1.0
      }
    },
    "MATERIAL": {
      "AlbedoPath": "../Platformer/Assets/Textures/Friend Base Color.png",
      "MetallicPath": "../Platformer/Assets/Textures/Ball Specular.png",
      "Alpha": 1.0,
      "wireMode": false
    },
    "COLLIDER": {
      "Shape": 0,
      "Radius": 2.930000066757202
    },
    "MOVING_BODY": {
      "Elasticity": 0.3499999940395355,
      "Friction": 0.0,
      "Gravity": true,
      "Mass": 5.0,
      "Velocity": {
        "x": 0.0,
        "y": -198.83291625976563,
        "z": 0.0
      },
      "Accelereation": {
        "x": 0.0,
        "y": 0.0,
        "z": 0.0
      },
      "CollisionType": 0,
      "Shape": 0,
      "Radius": 1.0
    },
    "GAME_LOGIC": [
      "PLATFORMER_BALL"
    ],
    "TAG": {
      "uniqueName": "ball",
      "category": "ball"
    }
  },
  {
    "MODEL": {
      "path": "../Platformer/Assets/models/Star.obj"
    },
    "TRANSFORM": {
      "position": {
        "x": 25.0,
        "y": 16.572999954223633,
        "z": 35.0
      },
      "scale": {
        "x": 3.0,
        "y": 3.0,
        "z": 3.0
      },
      "rotation": {
        "x": 0.0,
        "y": 0.0,
        "z": 0.0,
        "w": 1.0
      }
    },
    "MATERIAL": {
      "AlbedoPath": "../Platformer/Assets/Textures/Star Base Color.png",
      "MetallicPath": "../Platformer/Assets/Textures/Ball Specular.png",
      "Alpha": 1.0,
      "wireMode": false
    },
    "COLLIDER": {
      "Shape": 0,
      "Radius": 3.0
    },
    "GAME_LOGIC": [
      "STAR"
    ],
    "TAG": {
      "uniqueName": "Star",
      "category": "Star"
    }
  }
]